maha_cet_parser/__init__.py
maha_cet_parser/main.py
maha_cet_parser/admission_enums/AdmissionEnums.py
maha_cet_parser/admission_enums/__init__.py
maha_cet_parser/commands/Commands.py
maha_cet_parser/commands/CreateTableMySQL.py
maha_cet_parser/commands/MahaCETEngineering.py
maha_cet_parser/commands/__init__.py
maha_cet_parser/db/__init__.py
maha_cet_parser/db/db.py
maha_cet_parser/models/__init__.py
maha_cet_parser/models/admission.py
maha_cet_parser/models/admissioncutoff.py
maha_cet_parser/models/branch.py
maha_cet_parser/models/collage.py
maha_cet_parser/models/student.py
maha_cet_parser/models/university.py
maha_cet_parser/resources/__init__.py
maha_cet_parser/resources/engg/__init__.py
maha_cet_parser/resources/engg/pg/__init__.py
maha_cet_parser/resources/engg/ug/__init__.py
maha_cet_parser/resources/engg/ug/2017-18/__init__.py
maha_cet_parser/resources/engg/ug/2017-18/MH/MHT-CET-2017-18-Cutoff-Round-1-MH.xlsx
maha_cet_parser/resources/engg/ug/2017-18/MH/MHT-CET-2017-18-Cutoff-Round-2-MH.xlsx
maha_cet_parser/resources/engg/ug/2017-18/MH/MHT-CET-2017-18-Cutoff-Round-3-MH.xlsx
maha_cet_parser/resources/engg/ug/2017-18/MH/MHT-CET-2017-18-Cutoff-Round-4-MH.xlsx
maha_cet_parser/resources/engg/ug/2017-18/MH/__init__.py
maha_cet_parser/resources/engg/ug/2018-19/__init__.py
maha_cet_parser/resources/engg/ug/2018-19/MH/MHT-CET-2018-19-Cutoff-Round-1-MH.xlsx
maha_cet_parser/resources/engg/ug/2018-19/MH/MHT-CET-2018-19-Cutoff-Round-2-MH.xlsx
maha_cet_parser/resources/engg/ug/2018-19/MH/MHT-CET-2018-19-Cutoff-Round-3-MH.xlsx
maha_cet_parser/resources/engg/ug/2018-19/MH/MHT-CET-2018-19-Cutoff-Round-4-MH.xlsx
maha_cet_parser/resources/engg/ug/2018-19/MH/__init__.py
maha_cet_parser/resources/engg/ug/2019-20/__init__.py
maha_cet_parser/resources/engg/ug/2019-20/MH/MHT-CET-2019-20-Cutoff-Round-1-MH.xlsx
maha_cet_parser/resources/engg/ug/2019-20/MH/MHT-CET-2019-20-Cutoff-Round-2-MH.xlsx
maha_cet_parser/resources/engg/ug/2019-20/MH/MHT-CET-2019-20-Cutoff-Round-3-MH.xlsx
mh_admission-1.1.1.dist-info/METADATA
mh_admission-1.1.1.dist-info/WHEEL
mh_admission-1.1.1.dist-info/entry_points.txt
mh_admission-1.1.1.dist-info/top_level.txt
mh_admission-1.1.1.dist-info/RECORD
