Metadata-Version: 2.1
Name: mh-admission
Version: 1.1.1
Summary: Maharashtra admission tools
Home-page: https://gitlab.com/prasad.deshpande13/mh_cet_admission_utils
Author: Deshpande Prasad S.
Author-email: prasad.deshpande13@gmail.com
License: UNKNOWN
Platform: UNKNOWN
Requires-Dist: SQLAlchemy (~=1.3.1)
Requires-Dist: ConfigArgParse (~=1.0)
Requires-Dist: xlrd (~=1.2.0)
Requires-Dist: setuptools (~=46.1.3)
Requires-Dist: pymysql
